{
  "classname": null,
  "name": null,
  "animation": {
    "classname": null,
    "name": "AnimationManager",
    "actionlist": []
  },
  "designHeight": 480,
  "designWidth": 320,
  "textures": [],
  "version": "1.0.0.0",
  "widgetTree": {
    "classname": "Panel",
    "name": null,
    "children": [
      {
        "classname": "Button",
        "name": null,
        "children": [],
        "options": {
          "__type": "ComGUIButtonSurrogate:#EditorCommon.JsonModel.Component.GUI",
          "classname": "Button",
          "name": "Callfriend_ok",
          "ZOrder": 6,
          "actiontag": 29,
          "anchorPointX": 0.5,
          "anchorPointY": 0.5,
          "classType": null,
          "colorB": 255,
          "colorG": 255,
          "colorR": 255,
          "flipX": false,
          "flipY": false,
          "height": 59,
          "ignoreSize": true,
          "opacity": 255,
          "rotation": 0,
          "scaleX": 1,
          "scaleY": 1,
          "tag": 9,
          "touchAble": true,
          "useMergedTexture": false,
          "visible": true,
          "width": 102,
          "x": 259,
          "xProportion": 0.809375,
          "y": 50,
          "yProportion": 0.104166664,
          "capInsetsHeight": 0,
          "capInsetsWidth": 0,
          "capInsetsX": 0,
          "capInsetsY": 0,
          "disabled": null,
          "disabledData": {
            "path": null,
            "plistFile": null,
            "resourceType": 0
          },
          "normal": null,
          "normalData": {
            "path": "ok_PanalCallfriend.png",
            "plistFile": null,
            "resourceType": 0
          },
          "pressed": null,
          "pressedData": {
            "path": null,
            "plistFile": null,
            "resourceType": 0
          },
          "scale9Enable": false,
          "scale9Height": 59,
          "scale9Width": 102
        }
      },
      {
        "classname": "TextButton",
        "name": null,
        "children": [],
        "options": {
          "__type": "ComGUITextButtonSurrogate:#EditorCommon.JsonModel.Component.GUI",
          "classname": "TextButton",
          "name": "Callfriend_5",
          "ZOrder": 5,
          "actiontag": 26,
          "anchorPointX": 0.5,
          "anchorPointY": 0.5,
          "classType": null,
          "colorB": 255,
          "colorG": 255,
          "colorR": 255,
          "flipX": false,
          "flipY": false,
          "height": 54,
          "ignoreSize": true,
          "opacity": 255,
          "rotation": 0,
          "scaleX": 1,
          "scaleY": 1,
          "tag": 6,
          "touchAble": true,
          "useMergedTexture": false,
          "visible": true,
          "width": 155,
          "x": 160,
          "xProportion": 0.5,
          "y": 126,
          "yProportion": 0.2625,
          "capInsetsHeight": 0,
          "capInsetsWidth": 0,
          "capInsetsX": 0,
          "capInsetsY": 0,
          "disabled": null,
          "disabledData": {
            "path": null,
            "plistFile": null,
            "resourceType": 0
          },
          "fontName": "宋体",
          "fontSize": 20,
          "fontType": 0,
          "normal": null,
          "normalData": {
            "path": "chose_PanalCallfriend.png",
            "plistFile": null,
            "resourceType": 0
          },
          "pressed": null,
          "pressedData": {
            "path": null,
            "plistFile": null,
            "resourceType": 0
          },
          "scale9Enable": false,
          "scale9Height": 54,
          "scale9Width": 155,
          "text": "Text Button",
          "textColorB": 255,
          "textColorG": 255,
          "textColorR": 255
        }
      },
      {
        "classname": "TextButton",
        "name": null,
        "children": [],
        "options": {
          "__type": "ComGUITextButtonSurrogate:#EditorCommon.JsonModel.Component.GUI",
          "classname": "TextButton",
          "name": "Callfriend_4",
          "ZOrder": 4,
          "actiontag": 25,
          "anchorPointX": 0.5,
          "anchorPointY": 0.5,
          "classType": null,
          "colorB": 255,
          "colorG": 255,
          "colorR": 255,
          "flipX": false,
          "flipY": false,
          "height": 54,
          "ignoreSize": true,
          "opacity": 255,
          "rotation": 0,
          "scaleX": 1,
          "scaleY": 1,
          "tag": 5,
          "touchAble": true,
          "useMergedTexture": false,
          "visible": true,
          "width": 155,
          "x": 160,
          "xProportion": 0.5,
          "y": 204,
          "yProportion": 0.425,
          "capInsetsHeight": 0,
          "capInsetsWidth": 0,
          "capInsetsX": 0,
          "capInsetsY": 0,
          "disabled": null,
          "disabledData": {
            "path": null,
            "plistFile": null,
            "resourceType": 0
          },
          "fontName": "宋体",
          "fontSize": 20,
          "fontType": 0,
          "normal": null,
          "normalData": {
            "path": "chose_PanalCallfriend.png",
            "plistFile": null,
            "resourceType": 0
          },
          "pressed": null,
          "pressedData": {
            "path": null,
            "plistFile": null,
            "resourceType": 0
          },
          "scale9Enable": false,
          "scale9Height": 54,
          "scale9Width": 155,
          "text": "Text Button",
          "textColorB": 255,
          "textColorG": 255,
          "textColorR": 255
        }
      },
      {
        "classname": "TextButton",
        "name": null,
        "children": [],
        "options": {
          "__type": "ComGUITextButtonSurrogate:#EditorCommon.JsonModel.Component.GUI",
          "classname": "TextButton",
          "name": "Callfriend_3",
          "ZOrder": 3,
          "actiontag": 24,
          "anchorPointX": 0.5,
          "anchorPointY": 0.5,
          "classType": null,
          "colorB": 255,
          "colorG": 255,
          "colorR": 255,
          "flipX": false,
          "flipY": false,
          "height": 54,
          "ignoreSize": true,
          "opacity": 255,
          "rotation": 0,
          "scaleX": 1,
          "scaleY": 1,
          "tag": 4,
          "touchAble": true,
          "useMergedTexture": false,
          "visible": true,
          "width": 155,
          "x": 160,
          "xProportion": 0.5,
          "y": 281,
          "yProportion": 0.5854167,
          "capInsetsHeight": 0,
          "capInsetsWidth": 0,
          "capInsetsX": 0,
          "capInsetsY": 0,
          "disabled": null,
          "disabledData": {
            "path": null,
            "plistFile": null,
            "resourceType": 0
          },
          "fontName": "宋体",
          "fontSize": 20,
          "fontType": 0,
          "normal": null,
          "normalData": {
            "path": "chose_PanalCallfriend.png",
            "plistFile": null,
            "resourceType": 0
          },
          "pressed": null,
          "pressedData": {
            "path": null,
            "plistFile": null,
            "resourceType": 0
          },
          "scale9Enable": false,
          "scale9Height": 54,
          "scale9Width": 155,
          "text": "Text Button",
          "textColorB": 255,
          "textColorG": 255,
          "textColorR": 255
        }
      },
      {
        "classname": "TextButton",
        "name": null,
        "children": [],
        "options": {
          "__type": "ComGUITextButtonSurrogate:#EditorCommon.JsonModel.Component.GUI",
          "classname": "TextButton",
          "name": "Callfriend_2",
          "ZOrder": 2,
          "actiontag": 23,
          "anchorPointX": 0.5,
          "anchorPointY": 0.5,
          "classType": null,
          "colorB": 255,
          "colorG": 255,
          "colorR": 255,
          "flipX": false,
          "flipY": false,
          "height": 54,
          "ignoreSize": true,
          "opacity": 255,
          "rotation": 0,
          "scaleX": 1,
          "scaleY": 1,
          "tag": 3,
          "touchAble": true,
          "useMergedTexture": false,
          "visible": true,
          "width": 155,
          "x": 159,
          "xProportion": 0.496875,
          "y": 360,
          "yProportion": 0.75,
          "capInsetsHeight": 0,
          "capInsetsWidth": 0,
          "capInsetsX": 0,
          "capInsetsY": 0,
          "disabled": null,
          "disabledData": {
            "path": null,
            "plistFile": null,
            "resourceType": 0
          },
          "fontName": "宋体",
          "fontSize": 20,
          "fontType": 0,
          "normal": null,
          "normalData": {
            "path": "chose_PanalCallfriend.png",
            "plistFile": null,
            "resourceType": 0
          },
          "pressed": null,
          "pressedData": {
            "path": null,
            "plistFile": null,
            "resourceType": 0
          },
          "scale9Enable": false,
          "scale9Height": 54,
          "scale9Width": 155,
          "text": "Text Button",
          "textColorB": 255,
          "textColorG": 255,
          "textColorR": 255
        }
      },
      {
        "classname": "TextButton",
        "name": null,
        "children": [],
        "options": {
          "__type": "ComGUITextButtonSurrogate:#EditorCommon.JsonModel.Component.GUI",
          "classname": "TextButton",
          "name": "Callfriend_1",
          "ZOrder": 1,
          "actiontag": 22,
          "anchorPointX": 0.5,
          "anchorPointY": 0.5,
          "classType": null,
          "colorB": 255,
          "colorG": 255,
          "colorR": 255,
          "flipX": false,
          "flipY": false,
          "height": 54,
          "ignoreSize": true,
          "opacity": 255,
          "rotation": 0,
          "scaleX": 1,
          "scaleY": 1,
          "tag": 2,
          "touchAble": true,
          "useMergedTexture": false,
          "visible": true,
          "width": 155,
          "x": 160,
          "xProportion": 0.5,
          "y": 424,
          "yProportion": 0.8833333,
          "capInsetsHeight": 0,
          "capInsetsWidth": 0,
          "capInsetsX": 0,
          "capInsetsY": 0,
          "disabled": null,
          "disabledData": {
            "path": null,
            "plistFile": null,
            "resourceType": 0
          },
          "fontName": "宋体",
          "fontSize": 20,
          "fontType": 0,
          "normal": null,
          "normalData": {
            "path": "chose_PanalCallfriend.png",
            "plistFile": null,
            "resourceType": 0
          },
          "pressed": null,
          "pressedData": {
            "path": null,
            "plistFile": null,
            "resourceType": 0
          },
          "scale9Enable": false,
          "scale9Height": 54,
          "scale9Width": 155,
          "text": "Text Button",
          "textColorB": 255,
          "textColorG": 255,
          "textColorR": 255
        }
      }
    ],
    "options": {
      "__type": "ComGUIPanelSurrogate:#EditorCommon.JsonModel.Component.GUI",
      "classname": "Panel",
      "name": "PanelCallfriend",
      "ZOrder": 0,
      "actiontag": -1,
      "anchorPointX": 0,
      "anchorPointY": 0,
      "classType": null,
      "colorB": 255,
      "colorG": 255,
      "colorR": 255,
      "flipX": false,
      "flipY": false,
      "height": 480,
      "ignoreSize": false,
      "opacity": 255,
      "rotation": 0,
      "scaleX": 1,
      "scaleY": 1,
      "tag": 1,
      "touchAble": false,
      "useMergedTexture": false,
      "visible": true,
      "width": 320,
      "x": 0,
      "xProportion": 0,
      "y": 0,
      "yProportion": 0,
      "backGroundImage": null,
      "backGroundImageData": null,
      "backGroundScale9Enable": false,
      "bgColorB": 255,
      "bgColorG": 200,
      "bgColorOpacity": 0,
      "bgColorR": 150,
      "bgEndColorB": 0,
      "bgEndColorG": 128,
      "bgEndColorR": 0,
      "bgStartColorB": 0,
      "bgStartColorG": 0,
      "bgStartColorR": 255,
      "capInsetsHeight": 0,
      "capInsetsWidth": 0,
      "capInsetsX": 0,
      "capInsetsY": 0,
      "clipAble": false,
      "colorType": 2,
      "vectorX": 0,
      "vectorY": -0.5
    }
  }
}